flask_fd/__init__.py
flask_fd/__main__.py
flask_fd/cmd.py
flask_fd/helpers.py
flask_fd/gui/__init__.py
flask_fd/gui/builder.py
flask_fd/gui/containers.py
flask_fd/gui/header_bar.py
flask_fd/gui/helpers.py
flask_fd/gui/indicators.py
flask_fd/gui/menus.py
flask_fd/gui/web.py
flask_fd/launchers/__init__.py
flask_fd/launchers/launchers.py
flask_fd/plop/__init__.py
flask_fd/plop/ploppers.py
flask_fd/plop/flask/main_flask_fd_1.py
flask_fd/plop/flask/main_flask_fd_2.py
flask_fd/plop/flask/main_flask_fd_3.py
flask_fd/plop/flask/starter/__init__.py
flask_fd/plop/flask/starter/flask_for_desktop.py
flask_fd/plop/flask/starter/flaskapp/__init__.py
flask_fd/plop/flask/starter/flaskapp/main.py
flask_fd/plop/flask/starter/flaskapp/shell_context.py
flask_fd/plop/flask/starter/flaskapp/app/__init__.py
flask_fd/plop/flask/starter/flaskapp/app/config.py
flask_fd/plop/flask/starter/flaskapp/app/models.py
flask_fd/plop/flask/starter/flaskapp/app/views.py
flask_fd/plop/flask/starter/flaskapp/app/static/__init__.py
flask_fd/plop/flask/starter/flaskapp/app/static/css/__init__.py
flask_fd/plop/flask/starter/flaskapp/app/static/img/FlaskFdIcon
flask_fd/plop/flask/starter/flaskapp/app/static/img/__init__.py
flask_fd/plop/flask/starter/flaskapp/app/static/js/__init__.py
flask_fd/plop/flask/starter/flaskapp/app/templates/__init__.py
flask_fd/plop/flask/starter/flaskapp/app/templates/_base.html
flask_fd/plop/flask/starter/flaskapp/app/templates/index.html
flask_fd-1.1.2.dist-info/LICENSE.md
flask_fd-1.1.2.dist-info/METADATA
flask_fd-1.1.2.dist-info/WHEEL
flask_fd-1.1.2.dist-info/entry_points.txt
flask_fd-1.1.2.dist-info/top_level.txt
flask_fd-1.1.2.dist-info/RECORD
