Metadata-Version: 2.1
Name: flask-fd
Version: 1.1.2
Summary: Use flask to create desktop applications
Home-page: https://github.com/byoso/flask_for_desktop
Author: Vincent Fabre
Author-email: peigne.plume@gmail.com
License: MIT
Keywords: flask desktop gui
Platform: UNKNOWN
Classifier: License :: OSI Approved :: MIT License
Classifier: Programming Language :: Python :: 3
Classifier: Development Status :: 5 - Production/Stable
Classifier: License :: OSI Approved :: MIT License
Classifier: Natural Language :: English
Requires-Python: >=3.6
License-File: LICENSE.md
Requires-Dist: flamewok (>=1.2.1)
Requires-Dist: flask-migrate
Requires-Dist: flask-sqlalchemy
